[
  {
    "id": "6dd9072c-8a8f-492e-be76-1a70b95c27c8",
    "data": [
      {
        "text": "holiday in ",
        "userDefined": false
      },
      {
        "text": "April",
        "meta": "@sys.ignore",
        "userDefined": false
      }
    ],
    "isTemplate": false,
    "count": 0,
    "lang": "en",
    "updated": 0
  },
  {
    "id": "b15d77da-5660-4378-96a0-d15a76f9013f",
    "data": [
      {
        "text": "Is there any holiday in ",
        "userDefined": false
      },
      {
        "text": "April",
        "meta": "@sys.ignore",
        "userDefined": false
      }
    ],
    "isTemplate": false,
    "count": 0,
    "lang": "en",
    "updated": 0
  }
]