[
  {
    "id": "69ddb803-39cd-4345-a068-ae66750b8105",
    "data": [
      {
        "text": "12",
        "meta": "@sys.ignore",
        "userDefined": false
      },
      {
        "text": " A\u0027s",
        "userDefined": false
      }
    ],
    "isTemplate": false,
    "count": 0,
    "lang": "en",
    "updated": 0
  },
  {
    "id": "95d1edab-3732-41e6-bb6e-e2ee73dea62c",
    "data": [
      {
        "text": "12",
        "meta": "@sys.ignore",
        "userDefined": false
      },
      {
        "text": " A",
        "userDefined": false
      }
    ],
    "isTemplate": false,
    "count": 0,
    "lang": "en",
    "updated": 0
  },
  {
    "id": "4b558949-531e-418a-a414-9bf295f5af50",
    "data": [
      {
        "text": "12",
        "meta": "@sys.ignore",
        "userDefined": false
      }
    ],
    "isTemplate": false,
    "count": 0,
    "lang": "en",
    "updated": 0
  },
  {
    "id": "21b522de-0fc0-44f8-92fa-3a685d72c336",
    "data": [
      {
        "text": "11",
        "meta": "@sys.ignore",
        "userDefined": false
      },
      {
        "text": " A\u0027s",
        "userDefined": false
      }
    ],
    "isTemplate": false,
    "count": 0,
    "lang": "en",
    "updated": 0
  },
  {
    "id": "b51bb647-fedb-45af-8d8d-26944654afff",
    "data": [
      {
        "text": "11",
        "meta": "@sys.ignore",
        "userDefined": false
      },
      {
        "text": " A",
        "userDefined": false
      }
    ],
    "isTemplate": false,
    "count": 0,
    "lang": "en",
    "updated": 0
  },
  {
    "id": "ad6c5d7e-103c-4706-aac5-8986f2c1d03a",
    "data": [
      {
        "text": "11",
        "meta": "@sys.ignore",
        "userDefined": false
      }
    ],
    "isTemplate": false,
    "count": 0,
    "lang": "en",
    "updated": 0
  },
  {
    "id": "def57d72-3ac7-4052-b0e1-af0a37c964b3",
    "data": [
      {
        "text": "10",
        "meta": "@sys.ignore",
        "userDefined": false
      },
      {
        "text": " A\u0027s",
        "userDefined": false
      }
    ],
    "isTemplate": false,
    "count": 0,
    "lang": "en",
    "updated": 0
  },
  {
    "id": "f62795ac-68a9-4cd9-80fb-50eed21ce22b",
    "data": [
      {
        "text": "10",
        "meta": "@sys.ignore",
        "userDefined": false
      },
      {
        "text": " A",
        "userDefined": false
      }
    ],
    "isTemplate": false,
    "count": 0,
    "lang": "en",
    "updated": 0
  },
  {
    "id": "bafb665b-46f3-4f78-a7fb-8f698eb1f75d",
    "data": [
      {
        "text": "10",
        "meta": "@sys.ignore",
        "userDefined": false
      }
    ],
    "isTemplate": false,
    "count": 0,
    "lang": "en",
    "updated": 0
  }
]